writestat_mcp/__init__.py
writestat_mcp/cli.py
writestat_mcp/server.py
writestat_mcp/validation.py
writestat_mcp/analyzers/__init__.py
writestat_mcp/analyzers/ai_patterns.py
writestat_mcp/analyzers/ml_detector.py
writestat_mcp/analyzers/readability.py
writestat_mcp/analyzers/sentences.py
writestat_mcp/models/__init__.py
writestat_mcp/models/results.py
writestat_mcp-0.1.0.dist-info/METADATA
writestat_mcp-0.1.0.dist-info/WHEEL
writestat_mcp-0.1.0.dist-info/entry_points.txt
writestat_mcp-0.1.0.dist-info/licenses/LICENSE
writestat_mcp-0.1.0.dist-info/RECORD
