Metadata-Version: 2.4
Name: writestat-mcp
Version: 0.1.0
Summary: MCP server for text readability analysis and AI content detection with ML-based scoring
Project-URL: Homepage, https://github.com/labeveryday/writestat-mcp
Project-URL: Documentation, https://github.com/labeveryday/writestat-mcp#readme
Project-URL: Repository, https://github.com/labeveryday/writestat-mcp
Project-URL: Issues, https://github.com/labeveryday/writestat-mcp/issues
Author-email: Du'An Lightfoot <29664932+labeveryday@users.noreply.github.com>
License-Expression: MIT
License-File: LICENSE
Keywords: ai-detection,claude,fastmcp,mcp,nlp,readability,text-analysis
Classifier: Development Status :: 4 - Beta
Classifier: Intended Audience :: Developers
Classifier: License :: OSI Approved :: MIT License
Classifier: Programming Language :: Python :: 3
Classifier: Programming Language :: Python :: 3.10
Classifier: Programming Language :: Python :: 3.11
Classifier: Programming Language :: Python :: 3.12
Classifier: Programming Language :: Python :: 3.13
Classifier: Topic :: Scientific/Engineering :: Artificial Intelligence
Classifier: Topic :: Text Processing :: Linguistic
Requires-Python: >=3.10
Requires-Dist: mcp>=1.0.0
Requires-Dist: nltk>=3.8
Requires-Dist: textstat>=0.7.3
Provides-Extra: dev
Requires-Dist: black>=23.0.0; extra == 'dev'
Requires-Dist: pytest-asyncio>=0.21.0; extra == 'dev'
Requires-Dist: pytest>=7.0.0; extra == 'dev'
Requires-Dist: ruff>=0.1.0; extra == 'dev'
Provides-Extra: ml
Requires-Dist: torch>=2.0.0; extra == 'ml'
Requires-Dist: transformers>=4.30.0; extra == 'ml'
